[{"symbol":"PTTGC","date":"29/01/2559","open":"52.50","high":"53.75","low":"51.50","close":"53.75","volume":"33,177,442"},{"symbol":"PTTGC","date":"28/01/2559","open":"51.00","high":"51.75","low":"49.75","close":"51.50","volume":"23,845,508"},{"symbol":"PTTGC","date":"27/01/2559","open":"51.00","high":"51.75","low":"50.00","close":"50.25","volume":"17,117,361"},{"symbol":"PTTGC","date":"26/01/2559","open":"48.50","high":"49.75","low":"48.50","close":"49.75","volume":"11,166,775"},{"symbol":"PTTGC","date":"25/01/2559","open":"50.00","high":"52.50","low":"49.75","close":"50.00","volume":"33,930,261"},{"symbol":"PTTGC","date":"22/01/2559","open":"48.75","high":"49.75","low":"47.75","close":"49.25","volume":"19,014,320"},{"symbol":"PTTGC","date":"21/01/2559","open":"48.00","high":"48.75","low":"47.00","close":"47.50","volume":"12,327,337"},{"symbol":"PTTGC","date":"20/01/2559","open":"46.50","high":"47.50","low":"46.00","close":"47.00","volume":"12,077,983"},{"symbol":"PTTGC","date":"19/01/2559","open":"45.75","high":"49.00","low":"45.75","close":"47.25","volume":"22,842,905"},{"symbol":"PTTGC","date":"18/01/2559","open":"44.50","high":"45.75","low":"44.25","close":"45.00","volume":"17,744,101"},{"symbol":"PTTGC","date":"15/01/2559","open":"48.50","high":"49.00","low":"45.50","close":"45.75","volume":"19,616,649"},{"symbol":"PTTGC","date":"14/01/2559","open":"48.50","high":"49.25","low":"47.75","close":"48.50","volume":"16,197,915"},{"symbol":"PTTGC","date":"13/01/2559","open":"47.00","high":"50.00","low":"46.50","close":"50.00","volume":"21,084,174"},{"symbol":"PTTGC","date":"12/01/2559","open":"44.75","high":"46.00","low":"44.25","close":"45.75","volume":"14,970,460"},{"symbol":"PTTGC","date":"11/01/2559","open":"45.75","high":"46.00","low":"44.25","close":"45.25","volume":"12,745,553"},{"symbol":"PTTGC","date":"08/01/2559","open":"46.25","high":"47.25","low":"46.00","close":"47.00","volume":"13,795,044"},{"symbol":"PTTGC","date":"07/01/2559","open":"46.75","high":"47.25","low":"45.25","close":"45.50","volume":"22,175,865"},{"symbol":"PTTGC","date":"06/01/2559","open":"48.75","high":"49.50","low":"48.50","close":"49.25","volume":"9,005,159"},{"symbol":"PTTGC","date":"05/01/2559","open":"49.75","high":"50.75","low":"49.50","close":"49.50","volume":"9,440,528"},{"symbol":"PTTGC","date":"04/01/2559","open":"50.00","high":"51.00","low":"49.75","close":"50.00","volume":"5,403,796"},{"symbol":"PTTGC","date":"30/12/2558","open":"51.00","high":"51.25","low":"50.00","close":"50.00","volume":"4,285,596"},{"symbol":"PTTGC","date":"29/12/2558","open":"51.00","high":"51.25","low":"49.50","close":"51.00","volume":"10,269,478"},{"symbol":"PTTGC","date":"28/12/2558","open":"52.25","high":"52.50","low":"51.50","close":"51.50","volume":"2,213,233"},{"symbol":"PTTGC","date":"25/12/2558","open":"52.00","high":"52.50","low":"51.25","close":"52.00","volume":"3,234,615"},{"symbol":"PTTGC","date":"24/12/2558","open":"50.75","high":"52.50","low":"50.50","close":"52.50","volume":"14,548,668"},{"symbol":"PTTGC","date":"23/12/2558","open":"49.00","high":"50.25","low":"48.75","close":"50.00","volume":"10,822,130"},{"symbol":"PTTGC","date":"22/12/2558","open":"49.50","high":"50.25","low":"48.25","close":"48.25","volume":"8,666,274"},{"symbol":"PTTGC","date":"21/12/2558","open":"49.00","high":"50.00","low":"48.50","close":"49.50","volume":"6,044,439"},{"symbol":"PTTGC","date":"18/12/2558","open":"50.50","high":"51.00","low":"49.25","close":"49.75","volume":"14,299,780"},{"symbol":"PTTGC","date":"17/12/2558","open":"51.75","high":"52.00","low":"50.50","close":"51.50","volume":"16,455,604"},{"symbol":"PTTGC","date":"16/12/2558","open":"52.50","high":"52.50","low":"51.50","close":"52.25","volume":"11,108,889"},{"symbol":"PTTGC","date":"15/12/2558","open":"50.50","high":"52.25","low":"49.75","close":"52.00","volume":"18,998,485"},{"symbol":"PTTGC","date":"14/12/2558","open":"47.25","high":"49.50","low":"46.50","close":"49.50","volume":"27,064,457"},{"symbol":"PTTGC","date":"11/12/2558","open":"49.50","high":"49.50","low":"48.50","close":"48.75","volume":"19,291,550"},{"symbol":"PTTGC","date":"09/12/2558","open":"50.50","high":"50.75","low":"49.50","close":"49.75","volume":"9,861,278"},{"symbol":"PTTGC","date":"08/12/2558","open":"50.25","high":"50.25","low":"49.00","close":"49.75","volume":"18,600,492"},{"symbol":"PTTGC","date":"04/12/2558","open":"52.00","high":"52.25","low":"50.50","close":"51.00","volume":"12,625,593"},{"symbol":"PTTGC","date":"03/12/2558","open":"52.50","high":"52.75","low":"51.75","close":"52.25","volume":"8,512,562"},{"symbol":"PTTGC","date":"02/12/2558","open":"53.00","high":"54.00","low":"52.25","close":"52.50","volume":"12,531,839"},{"symbol":"PTTGC","date":"01/12/2558","open":"53.25","high":"53.25","low":"51.75","close":"52.50","volume":"17,792,449"},{"symbol":"PTTGC","date":"30/11/2558","open":"53.75","high":"55.00","low":"52.75","close":"52.75","volume":"38,239,979"},{"symbol":"PTTGC","date":"27/11/2558","open":"54.25","high":"54.50","low":"53.50","close":"53.75","volume":"8,940,635"},{"symbol":"PTTGC","date":"26/11/2558","open":"55.50","high":"55.75","low":"54.25","close":"54.25","volume":"9,721,072"},{"symbol":"PTTGC","date":"25/11/2558","open":"55.50","high":"55.75","low":"54.75","close":"55.25","volume":"18,417,746"},{"symbol":"PTTGC","date":"24/11/2558","open":"56.50","high":"57.00","low":"55.50","close":"55.50","volume":"10,137,693"},{"symbol":"PTTGC","date":"23/11/2558","open":"57.25","high":"57.50","low":"56.25","close":"56.25","volume":"7,997,265"},{"symbol":"PTTGC","date":"20/11/2558","open":"57.00","high":"57.50","low":"56.75","close":"57.00","volume":"7,559,514"},{"symbol":"PTTGC","date":"19/11/2558","open":"57.00","high":"58.00","low":"56.25","close":"56.50","volume":"12,057,617"},{"symbol":"PTTGC","date":"18/11/2558","open":"56.75","high":"57.25","low":"55.50","close":"55.75","volume":"10,812,350"},{"symbol":"PTTGC","date":"17/11/2558","open":"58.00","high":"58.25","low":"56.50","close":"56.75","volume":"15,128,518"},{"symbol":"PTTGC","date":"16/11/2558","open":"56.50","high":"57.50","low":"55.75","close":"57.50","volume":"16,470,494"},{"symbol":"PTTGC","date":"13/11/2558","open":"56.00","high":"57.75","low":"55.75","close":"57.25","volume":"18,953,605"},{"symbol":"PTTGC","date":"12/11/2558","open":"54.50","high":"56.00","low":"54.25","close":"55.50","volume":"10,004,092"},{"symbol":"PTTGC","date":"11/11/2558","open":"55.00","high":"55.25","low":"54.50","close":"54.50","volume":"7,695,337"},{"symbol":"PTTGC","date":"10/11/2558","open":"54.75","high":"55.75","low":"54.25","close":"55.25","volume":"8,060,655"},{"symbol":"PTTGC","date":"09/11/2558","open":"56.00","high":"56.25","low":"54.50","close":"55.00","volume":"11,377,540"},{"symbol":"PTTGC","date":"06/11/2558","open":"56.75","high":"57.00","low":"56.50","close":"56.50","volume":"3,610,929"},{"symbol":"PTTGC","date":"05/11/2558","open":"57.50","high":"57.50","low":"56.50","close":"56.75","volume":"5,897,173"},{"symbol":"PTTGC","date":"04/11/2558","open":"57.50","high":"57.75","low":"57.00","close":"57.75","volume":"6,415,441"},{"symbol":"PTTGC","date":"03/11/2558","open":"58.00","high":"58.25","low":"56.25","close":"56.75","volume":"9,023,014"},{"symbol":"PTTGC","date":"02/11/2558","open":"55.75","high":"57.75","low":"55.75","close":"57.75","volume":"9,009,041"},{"symbol":"PTTGC","date":"30/10/2558","open":"55.25","high":"56.75","low":"55.25","close":"55.75","volume":"10,284,212"},{"symbol":"PTTGC","date":"29/10/2558","open":"56.50","high":"57.00","low":"55.25","close":"55.50","volume":"13,646,267"},{"symbol":"PTTGC","date":"28/10/2558","open":"57.75","high":"58.00","low":"56.00","close":"56.25","volume":"15,694,649"},{"symbol":"PTTGC","date":"27/10/2558","open":"58.75","high":"59.25","low":"58.00","close":"58.25","volume":"13,490,675"},{"symbol":"PTTGC","date":"26/10/2558","open":"59.75","high":"60.25","low":"59.00","close":"59.25","volume":"9,725,411"},{"symbol":"PTTGC","date":"22/10/2558","open":"58.75","high":"59.75","low":"58.50","close":"59.50","volume":"4,148,882"},{"symbol":"PTTGC","date":"21/10/2558","open":"59.25","high":"59.75","low":"59.00","close":"59.00","volume":"5,461,876"},{"symbol":"PTTGC","date":"20/10/2558","open":"59.75","high":"59.75","low":"59.00","close":"59.25","volume":"4,268,190"},{"symbol":"PTTGC","date":"19/10/2558","open":"60.00","high":"60.25","low":"59.50","close":"59.50","volume":"4,284,156"},{"symbol":"PTTGC","date":"16/10/2558","open":"60.75","high":"61.00","low":"59.50","close":"59.50","volume":"10,931,549"},{"symbol":"PTTGC","date":"15/10/2558","open":"60.50","high":"61.50","low":"60.25","close":"60.75","volume":"9,578,056"},{"symbol":"PTTGC","date":"14/10/2558","open":"59.25","high":"61.25","low":"59.00","close":"60.00","volume":"11,544,389"},{"symbol":"PTTGC","date":"13/10/2558","open":"59.75","high":"60.00","low":"58.50","close":"59.50","volume":"18,216,186"},{"symbol":"PTTGC","date":"12/10/2558","open":"60.50","high":"61.00","low":"59.75","close":"60.75","volume":"15,250,718"},{"symbol":"PTTGC","date":"09/10/2558","open":"61.25","high":"61.75","low":"59.75","close":"60.25","volume":"17,601,770"},{"symbol":"PTTGC","date":"08/10/2558","open":"60.00","high":"61.00","low":"59.50","close":"59.75","volume":"18,224,090"},{"symbol":"PTTGC","date":"07/10/2558","open":"57.25","high":"61.25","low":"56.75","close":"61.00","volume":"26,091,557"},{"symbol":"PTTGC","date":"06/10/2558","open":"56.75","high":"57.50","low":"56.25","close":"56.50","volume":"11,803,037"},{"symbol":"PTTGC","date":"05/10/2558","open":"53.00","high":"56.25","low":"53.00","close":"56.25","volume":"17,227,440"},{"symbol":"PTTGC","date":"02/10/2558","open":"53.25","high":"53.50","low":"52.50","close":"52.75","volume":"12,400,041"},{"symbol":"PTTGC","date":"01/10/2558","open":"53.50","high":"54.00","low":"53.25","close":"53.50","volume":"6,075,650"},{"symbol":"PTTGC","date":"22/03/2559","open":"60.75","high":"60.75","low":"59.00","close":"59.25","volume":"10,911,663"},{"symbol":"PTTGC","date":"21/03/2559","open":"59.75","high":"60.75","low":"59.75","close":"60.75","volume":"11,913,682"},{"symbol":"PTTGC","date":"18/03/2559","open":"60.50","high":"61.25","low":"59.50","close":"59.50","volume":"14,694,358"},{"symbol":"PTTGC","date":"17/03/2559","open":"61.50","high":"61.50","low":"60.25","close":"60.25","volume":"20,240,698"},{"symbol":"PTTGC","date":"16/03/2559","open":"58.75","high":"59.25","low":"57.00","close":"59.00","volume":"17,189,460"},{"symbol":"PTTGC","date":"15/03/2559","open":"59.75","high":"60.50","low":"58.25","close":"58.50","volume":"16,236,297"},{"symbol":"PTTGC","date":"14/03/2559","open":"61.00","high":"62.75","low":"60.50","close":"61.25","volume":"27,880,519"},{"symbol":"PTTGC","date":"11/03/2559","open":"59.00","high":"60.00","low":"58.50","close":"59.50","volume":"14,731,494"},{"symbol":"PTTGC","date":"10/03/2559","open":"59.00","high":"59.00","low":"58.00","close":"58.50","volume":"6,964,300"},{"symbol":"PTTGC","date":"09/03/2559","open":"56.50","high":"58.50","low":"56.50","close":"58.50","volume":"11,015,569"},{"symbol":"PTTGC","date":"08/03/2559","open":"58.75","high":"59.25","low":"56.75","close":"56.75","volume":"20,179,783"},{"symbol":"PTTGC","date":"07/03/2559","open":"56.50","high":"59.75","low":"56.50","close":"59.00","volume":"24,476,099"},{"symbol":"PTTGC","date":"04/03/2559","open":"56.50","high":"57.00","low":"55.75","close":"55.75","volume":"12,178,042"},{"symbol":"PTTGC","date":"03/03/2559","open":"56.50","high":"56.50","low":"55.50","close":"56.25","volume":"16,627,989"},{"symbol":"PTTGC","date":"02/03/2559","open":"56.00","high":"56.25","low":"55.00","close":"55.25","volume":"17,259,867"},{"symbol":"PTTGC","date":"01/03/2559","open":"54.00","high":"55.25","low":"53.75","close":"55.25","volume":"9,933,699"},{"symbol":"PTTGC","date":"29/02/2559","open":"54.50","high":"55.00","low":"53.50","close":"53.75","volume":"10,541,719"},{"symbol":"PTTGC","date":"26/02/2559","open":"54.25","high":"55.25","low":"54.00","close":"54.75","volume":"10,234,517"},{"symbol":"PTTGC","date":"25/02/2559","open":"55.00","high":"55.25","low":"53.25","close":"53.75","volume":"8,844,912"},{"symbol":"PTTGC","date":"24/02/2559","open":"55.25","high":"56.25","low":"55.25","close":"55.75","volume":"18,152,806"},{"symbol":"PTTGC","date":"23/02/2559","open":"56.50","high":"57.25","low":"55.50","close":"56.50","volume":"18,769,878"},{"symbol":"PTTGC","date":"19/02/2559","open":"53.50","high":"56.25","low":"53.50","close":"56.00","volume":"19,897,056"},{"symbol":"PTTGC","date":"18/02/2559","open":"55.00","high":"55.00","low":"53.25","close":"53.75","volume":"31,345,211"},{"symbol":"PTTGC","date":"17/02/2559","open":"53.00","high":"53.50","low":"52.00","close":"53.50","volume":"13,879,842"},{"symbol":"PTTGC","date":"16/02/2559","open":"53.00","high":"54.50","low":"52.75","close":"53.25","volume":"32,172,568"},{"symbol":"PTTGC","date":"15/02/2559","open":"52.50","high":"53.00","low":"52.00","close":"53.00","volume":"11,763,305"},{"symbol":"PTTGC","date":"12/02/2559","open":"50.75","high":"51.50","low":"50.25","close":"51.50","volume":"9,457,283"},{"symbol":"PTTGC","date":"11/02/2559","open":"52.25","high":"52.25","low":"50.00","close":"50.00","volume":"14,933,798"},{"symbol":"PTTGC","date":"10/02/2559","open":"51.50","high":"52.75","low":"51.00","close":"52.75","volume":"10,161,678"},{"symbol":"PTTGC","date":"09/02/2559","open":"52.25","high":"52.25","low":"51.25","close":"52.00","volume":"17,369,843"},{"symbol":"PTTGC","date":"08/02/2559","open":"52.75","high":"53.50","low":"52.50","close":"53.00","volume":"4,332,953"},{"symbol":"PTTGC","date":"05/02/2559","open":"53.25","high":"53.50","low":"52.75","close":"53.00","volume":"9,592,310"},{"symbol":"PTTGC","date":"04/02/2559","open":"52.50","high":"53.25","low":"51.75","close":"53.25","volume":"22,608,386"},{"symbol":"PTTGC","date":"03/02/2559","open":"48.50","high":"51.00","low":"48.25","close":"51.00","volume":"12,940,316"},{"symbol":"PTTGC","date":"02/02/2559","open":"51.00","high":"52.00","low":"49.00","close":"49.00","volume":"21,819,225"},{"symbol":"PTTGC","date":"01/02/2559","open":"53.00","high":"53.75","low":"51.75","close":"51.75","volume":"21,750,042"}]