[{"symbol":"TOP","date":"29/01/2559","open":"64.00","high":"64.50","low":"63.50","close":"64.25","volume":"8,774,176"},{"symbol":"TOP","date":"28/01/2559","open":"66.75","high":"67.00","low":"62.75","close":"64.00","volume":"15,351,922"},{"symbol":"TOP","date":"27/01/2559","open":"65.50","high":"67.25","low":"65.00","close":"67.00","volume":"12,346,833"},{"symbol":"TOP","date":"26/01/2559","open":"64.50","high":"65.75","low":"64.50","close":"65.25","volume":"3,837,824"},{"symbol":"TOP","date":"25/01/2559","open":"66.75","high":"67.25","low":"65.25","close":"65.25","volume":"6,531,718"},{"symbol":"TOP","date":"22/01/2559","open":"64.75","high":"66.75","low":"64.00","close":"66.25","volume":"12,338,929"},{"symbol":"TOP","date":"21/01/2559","open":"65.00","high":"66.00","low":"63.75","close":"64.50","volume":"9,551,405"},{"symbol":"TOP","date":"20/01/2559","open":"64.75","high":"65.50","low":"64.50","close":"64.75","volume":"6,726,796"},{"symbol":"TOP","date":"19/01/2559","open":"65.75","high":"66.00","low":"64.50","close":"65.25","volume":"6,349,319"},{"symbol":"TOP","date":"18/01/2559","open":"67.25","high":"67.50","low":"66.00","close":"66.25","volume":"4,789,604"},{"symbol":"TOP","date":"15/01/2559","open":"67.00","high":"68.50","low":"66.75","close":"67.25","volume":"9,332,418"},{"symbol":"TOP","date":"14/01/2559","open":"66.00","high":"67.00","low":"65.00","close":"66.50","volume":"7,039,523"},{"symbol":"TOP","date":"13/01/2559","open":"66.00","high":"66.75","low":"65.50","close":"66.00","volume":"12,246,523"},{"symbol":"TOP","date":"12/01/2559","open":"65.00","high":"65.50","low":"64.50","close":"65.00","volume":"8,380,561"},{"symbol":"TOP","date":"11/01/2559","open":"63.50","high":"65.75","low":"63.25","close":"64.75","volume":"10,490,659"},{"symbol":"TOP","date":"08/01/2559","open":"63.50","high":"65.00","low":"63.00","close":"64.00","volume":"6,466,017"},{"symbol":"TOP","date":"07/01/2559","open":"64.50","high":"64.75","low":"62.75","close":"62.75","volume":"9,791,936"},{"symbol":"TOP","date":"06/01/2559","open":"64.00","high":"65.00","low":"63.25","close":"65.00","volume":"3,995,377"},{"symbol":"TOP","date":"05/01/2559","open":"63.50","high":"64.75","low":"62.50","close":"64.75","volume":"7,030,904"},{"symbol":"TOP","date":"04/01/2559","open":"65.25","high":"65.25","low":"62.25","close":"62.75","volume":"3,998,564"},{"symbol":"TOP","date":"30/12/2558","open":"64.50","high":"66.00","low":"64.25","close":"66.00","volume":"5,382,832"},{"symbol":"TOP","date":"29/12/2558","open":"63.50","high":"64.25","low":"63.00","close":"64.25","volume":"3,175,591"},{"symbol":"TOP","date":"28/12/2558","open":"63.25","high":"64.75","low":"63.25","close":"64.50","volume":"1,813,015"},{"symbol":"TOP","date":"25/12/2558","open":"63.75","high":"64.00","low":"62.25","close":"63.50","volume":"1,509,434"},{"symbol":"TOP","date":"24/12/2558","open":"65.00","high":"65.00","low":"63.50","close":"64.00","volume":"3,523,979"},{"symbol":"TOP","date":"23/12/2558","open":"63.50","high":"65.00","low":"63.50","close":"64.75","volume":"7,388,215"},{"symbol":"TOP","date":"22/12/2558","open":"62.50","high":"63.00","low":"61.50","close":"63.00","volume":"5,193,113"},{"symbol":"TOP","date":"21/12/2558","open":"61.00","high":"63.00","low":"60.50","close":"61.25","volume":"6,505,431"},{"symbol":"TOP","date":"18/12/2558","open":"60.50","high":"60.50","low":"60.00","close":"60.50","volume":"5,253,318"},{"symbol":"TOP","date":"17/12/2558","open":"61.50","high":"62.00","low":"59.75","close":"60.75","volume":"5,750,241"},{"symbol":"TOP","date":"16/12/2558","open":"60.25","high":"62.25","low":"60.00","close":"61.75","volume":"7,908,637"},{"symbol":"TOP","date":"15/12/2558","open":"58.00","high":"60.00","low":"57.75","close":"60.00","volume":"10,217,882"},{"symbol":"TOP","date":"14/12/2558","open":"58.25","high":"58.25","low":"56.50","close":"57.25","volume":"4,009,161"},{"symbol":"TOP","date":"11/12/2558","open":"58.00","high":"58.50","low":"57.50","close":"58.50","volume":"6,866,724"},{"symbol":"TOP","date":"09/12/2558","open":"57.25","high":"58.50","low":"57.25","close":"58.00","volume":"8,204,148"},{"symbol":"TOP","date":"08/12/2558","open":"56.25","high":"58.00","low":"56.00","close":"57.25","volume":"12,848,347"},{"symbol":"TOP","date":"04/12/2558","open":"59.00","high":"59.25","low":"58.75","close":"59.00","volume":"5,947,692"},{"symbol":"TOP","date":"03/12/2558","open":"59.50","high":"60.00","low":"58.50","close":"59.75","volume":"11,517,881"},{"symbol":"TOP","date":"02/12/2558","open":"61.00","high":"61.25","low":"59.50","close":"59.75","volume":"9,147,641"},{"symbol":"TOP","date":"01/12/2558","open":"59.25","high":"62.00","low":"59.00","close":"60.00","volume":"20,988,236"},{"symbol":"TOP","date":"30/11/2558","open":"60.00","high":"60.75","low":"58.25","close":"58.50","volume":"9,367,079"},{"symbol":"TOP","date":"27/11/2558","open":"59.00","high":"61.00","low":"58.50","close":"61.00","volume":"3,603,007"},{"symbol":"TOP","date":"26/11/2558","open":"61.50","high":"61.50","low":"58.50","close":"58.75","volume":"4,294,739"},{"symbol":"TOP","date":"25/11/2558","open":"62.00","high":"62.00","low":"61.00","close":"61.25","volume":"9,537,862"},{"symbol":"TOP","date":"24/11/2558","open":"61.75","high":"62.50","low":"60.25","close":"61.00","volume":"8,319,032"},{"symbol":"TOP","date":"23/11/2558","open":"63.00","high":"63.00","low":"60.75","close":"61.00","volume":"8,036,808"},{"symbol":"TOP","date":"20/11/2558","open":"62.50","high":"63.00","low":"62.25","close":"62.25","volume":"3,799,880"},{"symbol":"TOP","date":"19/11/2558","open":"61.75","high":"63.50","low":"61.50","close":"62.50","volume":"12,323,938"},{"symbol":"TOP","date":"18/11/2558","open":"61.50","high":"62.25","low":"61.00","close":"61.75","volume":"9,733,623"},{"symbol":"TOP","date":"17/11/2558","open":"62.25","high":"62.50","low":"60.50","close":"61.50","volume":"14,858,448"},{"symbol":"TOP","date":"16/11/2558","open":"59.50","high":"62.25","low":"58.75","close":"61.25","volume":"18,390,490"},{"symbol":"TOP","date":"13/11/2558","open":"57.50","high":"60.25","low":"57.50","close":"59.75","volume":"17,754,233"},{"symbol":"TOP","date":"12/11/2558","open":"57.00","high":"58.75","low":"56.50","close":"58.25","volume":"14,247,185"},{"symbol":"TOP","date":"11/11/2558","open":"55.50","high":"58.00","low":"55.50","close":"56.75","volume":"10,184,514"},{"symbol":"TOP","date":"10/11/2558","open":"54.50","high":"55.50","low":"54.25","close":"55.25","volume":"2,165,974"},{"symbol":"TOP","date":"09/11/2558","open":"55.75","high":"56.00","low":"54.50","close":"54.75","volume":"2,834,271"},{"symbol":"TOP","date":"06/11/2558","open":"54.50","high":"56.00","low":"54.25","close":"56.00","volume":"4,156,061"},{"symbol":"TOP","date":"05/11/2558","open":"55.50","high":"55.75","low":"55.00","close":"55.00","volume":"2,208,870"},{"symbol":"TOP","date":"04/11/2558","open":"56.25","high":"56.50","low":"55.75","close":"55.75","volume":"5,991,829"},{"symbol":"TOP","date":"03/11/2558","open":"56.25","high":"56.25","low":"55.25","close":"55.75","volume":"1,441,135"},{"symbol":"TOP","date":"02/11/2558","open":"54.50","high":"56.25","low":"54.25","close":"56.00","volume":"3,408,404"},{"symbol":"TOP","date":"30/10/2558","open":"54.00","high":"54.75","low":"54.00","close":"54.25","volume":"4,739,982"},{"symbol":"TOP","date":"29/10/2558","open":"55.00","high":"56.00","low":"54.25","close":"54.25","volume":"3,334,748"},{"symbol":"TOP","date":"28/10/2558","open":"55.50","high":"55.75","low":"54.25","close":"55.25","volume":"3,560,789"},{"symbol":"TOP","date":"27/10/2558","open":"56.50","high":"56.50","low":"55.50","close":"56.00","volume":"2,210,206"},{"symbol":"TOP","date":"26/10/2558","open":"56.75","high":"57.00","low":"55.75","close":"56.75","volume":"5,099,896"},{"symbol":"TOP","date":"22/10/2558","open":"56.25","high":"56.75","low":"55.00","close":"55.75","volume":"2,954,009"},{"symbol":"TOP","date":"21/10/2558","open":"57.00","high":"57.00","low":"56.25","close":"56.50","volume":"1,980,410"},{"symbol":"TOP","date":"20/10/2558","open":"56.50","high":"57.00","low":"56.00","close":"56.50","volume":"2,213,800"},{"symbol":"TOP","date":"19/10/2558","open":"56.50","high":"57.00","low":"56.00","close":"57.00","volume":"3,341,617"},{"symbol":"TOP","date":"16/10/2558","open":"55.75","high":"56.00","low":"55.00","close":"55.75","volume":"8,286,518"},{"symbol":"TOP","date":"15/10/2558","open":"54.50","high":"55.00","low":"54.25","close":"54.75","volume":"4,441,866"},{"symbol":"TOP","date":"14/10/2558","open":"54.50","high":"55.00","low":"54.25","close":"54.50","volume":"3,986,653"},{"symbol":"TOP","date":"13/10/2558","open":"55.00","high":"55.25","low":"53.75","close":"55.00","volume":"8,814,713"},{"symbol":"TOP","date":"12/10/2558","open":"56.00","high":"56.50","low":"55.00","close":"55.50","volume":"3,775,108"},{"symbol":"TOP","date":"09/10/2558","open":"57.00","high":"57.75","low":"55.75","close":"56.25","volume":"8,003,709"},{"symbol":"TOP","date":"08/10/2558","open":"56.75","high":"57.00","low":"55.75","close":"56.00","volume":"8,749,029"},{"symbol":"TOP","date":"07/10/2558","open":"57.00","high":"57.75","low":"56.50","close":"57.25","volume":"11,728,405"},{"symbol":"TOP","date":"06/10/2558","open":"55.75","high":"57.75","low":"55.50","close":"56.00","volume":"10,376,443"},{"symbol":"TOP","date":"05/10/2558","open":"53.25","high":"55.50","low":"53.00","close":"55.50","volume":"13,256,511"},{"symbol":"TOP","date":"02/10/2558","open":"53.25","high":"53.25","low":"52.00","close":"52.25","volume":"2,659,168"},{"symbol":"TOP","date":"01/10/2558","open":"52.50","high":"53.75","low":"52.50","close":"53.25","volume":"3,271,804"},{"symbol":"TOP","date":"22/03/2559","open":"68.50","high":"69.25","low":"68.00","close":"68.75","volume":"5,501,199"},{"symbol":"TOP","date":"21/03/2559","open":"70.00","high":"70.00","low":"68.50","close":"69.25","volume":"3,439,694"},{"symbol":"TOP","date":"18/03/2559","open":"69.00","high":"70.25","low":"68.50","close":"70.00","volume":"13,947,993"},{"symbol":"TOP","date":"17/03/2559","open":"67.75","high":"70.75","low":"67.50","close":"69.50","volume":"21,756,788"},{"symbol":"TOP","date":"16/03/2559","open":"66.75","high":"67.75","low":"66.75","close":"67.25","volume":"6,493,888"},{"symbol":"TOP","date":"15/03/2559","open":"67.50","high":"68.00","low":"67.00","close":"67.00","volume":"5,709,496"},{"symbol":"TOP","date":"14/03/2559","open":"68.00","high":"68.75","low":"66.75","close":"67.75","volume":"7,510,870"},{"symbol":"TOP","date":"11/03/2559","open":"68.25","high":"68.25","low":"67.50","close":"67.75","volume":"7,433,521"},{"symbol":"TOP","date":"10/03/2559","open":"67.75","high":"68.75","low":"67.25","close":"68.25","volume":"10,452,177"},{"symbol":"TOP","date":"09/03/2559","open":"69.50","high":"70.00","low":"67.25","close":"68.00","volume":"8,016,890"},{"symbol":"TOP","date":"08/03/2559","open":"68.00","high":"68.00","low":"66.00","close":"67.00","volume":"8,502,105"},{"symbol":"TOP","date":"07/03/2559","open":"65.25","high":"68.00","low":"65.25","close":"68.00","volume":"8,832,089"},{"symbol":"TOP","date":"04/03/2559","open":"67.00","high":"67.25","low":"64.50","close":"64.75","volume":"6,239,276"},{"symbol":"TOP","date":"03/03/2559","open":"66.25","high":"68.00","low":"65.25","close":"66.25","volume":"12,000,207"},{"symbol":"TOP","date":"02/03/2559","open":"66.25","high":"66.25","low":"65.00","close":"65.50","volume":"5,956,523"},{"symbol":"TOP","date":"01/03/2559","open":"64.00","high":"65.75","low":"63.75","close":"65.75","volume":"10,579,224"},{"symbol":"TOP","date":"29/02/2559","open":"64.00","high":"64.50","low":"63.50","close":"63.50","volume":"2,876,737"},{"symbol":"TOP","date":"26/02/2559","open":"64.00","high":"64.50","low":"63.25","close":"64.25","volume":"4,213,995"},{"symbol":"TOP","date":"25/02/2559","open":"63.00","high":"63.50","low":"62.25","close":"63.50","volume":"8,305,540"},{"symbol":"TOP","date":"24/02/2559","open":"62.25","high":"62.75","low":"61.50","close":"62.50","volume":"6,725,785"},{"symbol":"TOP","date":"23/02/2559","open":"63.50","high":"64.00","low":"63.00","close":"64.00","volume":"10,702,241"},{"symbol":"TOP","date":"19/02/2559","open":"63.75","high":"64.00","low":"62.25","close":"63.50","volume":"10,791,496"},{"symbol":"TOP","date":"18/02/2559","open":"63.25","high":"65.00","low":"63.00","close":"63.75","volume":"12,231,945"},{"symbol":"TOP","date":"17/02/2559","open":"61.00","high":"62.50","low":"60.75","close":"62.50","volume":"8,518,748"},{"symbol":"TOP","date":"16/02/2559","open":"59.75","high":"62.25","low":"59.50","close":"60.75","volume":"14,758,661"},{"symbol":"TOP","date":"15/02/2559","open":"59.00","high":"60.25","low":"58.00","close":"59.00","volume":"19,313,529"},{"symbol":"TOP","date":"12/02/2559","open":"60.00","high":"60.75","low":"56.00","close":"58.00","volume":"16,078,214"},{"symbol":"TOP","date":"11/02/2559","open":"64.00","high":"64.50","low":"60.25","close":"60.25","volume":"14,129,527"},{"symbol":"TOP","date":"10/02/2559","open":"63.75","high":"64.25","low":"63.00","close":"63.25","volume":"5,511,766"},{"symbol":"TOP","date":"09/02/2559","open":"64.25","high":"64.50","low":"63.50","close":"64.25","volume":"4,883,383"},{"symbol":"TOP","date":"08/02/2559","open":"65.00","high":"65.00","low":"64.50","close":"64.50","volume":"2,281,309"},{"symbol":"TOP","date":"05/02/2559","open":"64.75","high":"65.50","low":"64.50","close":"64.75","volume":"6,802,476"},{"symbol":"TOP","date":"04/02/2559","open":"63.75","high":"65.00","low":"63.75","close":"64.75","volume":"5,624,783"},{"symbol":"TOP","date":"03/02/2559","open":"63.25","high":"64.75","low":"63.25","close":"64.75","volume":"5,721,787"},{"symbol":"TOP","date":"02/02/2559","open":"64.50","high":"65.00","low":"63.25","close":"63.25","volume":"8,792,212"},{"symbol":"TOP","date":"01/02/2559","open":"64.00","high":"64.75","low":"63.00","close":"64.50","volume":"9,434,311"}]